autoconf/__init__.py
autoconf/min_gpu_recommender.py
autoconf/AutoGluonModels/README.md
autoconf/AutoGluonModels/changelog.md
autoconf/AutoGluonModels/v1-1-0_ag-20251112_155927-refit-clone-opt/learner.pkl
autoconf/AutoGluonModels/v1-1-0_ag-20251112_155927-refit-clone-opt/metadata.json
autoconf/AutoGluonModels/v1-1-0_ag-20251112_155927-refit-clone-opt/predictor.pkl
autoconf/AutoGluonModels/v1-1-0_ag-20251112_155927-refit-clone-opt/version.txt
autoconf/AutoGluonModels/v1-1-0_ag-20251112_155927-refit-clone-opt/models/trainer.pkl
autoconf/AutoGluonModels/v1-1-0_ag-20251112_155927-refit-clone-opt/models/NeuralNetTorch_FULL/model.pkl
autoconf/AutoGluonModels/v1-1-0_ag-20251112_155927-refit-clone-opt/models/WeightedEnsemble_L2_FULL/model.pkl
autoconf/AutoGluonModels/v2-0-0_ag-20251113_154241-refit-clone-opt/learner.pkl
autoconf/AutoGluonModels/v2-0-0_ag-20251113_154241-refit-clone-opt/metadata.json
autoconf/AutoGluonModels/v2-0-0_ag-20251113_154241-refit-clone-opt/predictor.pkl
autoconf/AutoGluonModels/v2-0-0_ag-20251113_154241-refit-clone-opt/version.txt
autoconf/AutoGluonModels/v2-0-0_ag-20251113_154241-refit-clone-opt/models/trainer.pkl
autoconf/AutoGluonModels/v2-0-0_ag-20251113_154241-refit-clone-opt/models/CatBoost_FULL/model.pkl
autoconf/AutoGluonModels/v2-0-0_ag-20251113_154241-refit-clone-opt/models/NeuralNetTorch_FULL/model.pkl
autoconf/AutoGluonModels/v2-0-0_ag-20251113_154241-refit-clone-opt/models/WeightedEnsemble_L2_FULL/model.pkl
autoconf/AutoGluonModels/v2-0-0_ag-20251113_154241-refit-clone-opt/models/XGBoost_FULL/model.pkl
autoconf/AutoGluonModels/v2-0-0_ag-20251113_154241-refit-clone-opt/models/XGBoost_FULL/xgb.ubj
autoconf/test/__init__.py
autoconf/test/test_config_mapper.py
autoconf/test/test_recommender.py
autoconf/utils/__init__.py
autoconf/utils/config_mapper.py
autoconf/utils/pydantic_models.py
autoconf/utils/recommender.py
autoconf/utils/rule_based_classifier.py
autoconf/utils/autoconf_build/README.md
autoconf/utils/autoconf_build/__init__.py
ado_autoconf-1.4.1.dist-info/METADATA
ado_autoconf-1.4.1.dist-info/WHEEL
ado_autoconf-1.4.1.dist-info/entry_points.txt
ado_autoconf-1.4.1.dist-info/RECORD
