Metadata-Version: 2.4
Name: ado-autoconf
Version: 1.4.1
Summary: An AutoConf plugin that suggests the minimum number of gpus necessary to execute a Tuning job
Requires-Dist: ado-core>=1.2.3
Requires-Dist: autogluon-tabular[catboost,xgboost]==1.4.0
Requires-Dist: cloudpickle
Requires-Dist: fastai
Requires-Dist: pandas
Requires-Dist: pydantic
Requires-Dist: torch
Provides-Extra: libomp
Requires-Dist: autogluon-tabular[lightgbm]; extra == 'libomp'
